[
  {
    "inputs": [
      {
        "internalType": "address",
        "name": "_dataHashReader",
        "type": "address"
      }
    ],
    "stateMutability": "nonpayable",
    "type": "constructor"
  },
  {
    "anonymous": false,
    "inputs": [
      {
        "indexed": false,
        "internalType": "uint256",
        "name": "numHashes",
        "type": "uint256"
      },
      {
        "indexed": false,
        "internalType": "bytes32[]",
        "name": "hashes",
        "type": "bytes32[]"
      }
    ],
    "name": "DataHashesParsed",
    "type": "event"
  },
  {
    "inputs": [],
    "name": "submitBatch",
    "outputs": [],
    "stateMutability": "nonpayable",
    "type": "function"
  }
]
